[
  {
    "name": "楼外楼（孤山店）",
    "area": "西湖",
    "taste": "清淡",
    "mealType": "正餐",
    "avgPrice": 180,
    "isLocalFavorite": true,
    "isInfluencerHype": false,
    "reason": "西湖醋鱼、东坡肉经典杭帮菜",
    "avoidTips": "旺季需等位",
    "bookingUrl": "https://m.dianping.com/shoplist/0/searchkeyword_%E6%A5%BC%E5%A4%96%E6%A5%BC%EF%BC%88%E5%AD%A4%E5%B1%B1%E5%BA%97%EF%BC%89%20%E8%A5%BF%E6%B9%96",
    "address": "杭州市西湖区孤山路30号",
    "latitude": 30.284100000000002,
    "longitude": 120.13510000000001,
    "platform": "大众点评"
  },
  {
    "name": "知味观（仁和路店）",
    "area": "湖滨",
    "taste": "清淡",
    "mealType": "早餐",
    "avgPrice": 40,
    "isLocalFavorite": true,
    "isInfluencerHype": false,
    "reason": "小笼、猫耳朵、片儿川",
    "avoidTips": null,
    "bookingUrl": "https://m.dianping.com/shoplist/0/searchkeyword_%E7%9F%A5%E5%91%B3%E8%A7%82%EF%BC%88%E4%BB%81%E5%92%8C%E8%B7%AF%E5%BA%97%EF%BC%89%20%E6%B9%96%E6%BB%A8",
    "address": "杭州市上城区仁和路",
    "latitude": 30.2791,
    "longitude": 120.16510000000001,
    "platform": "大众点评"
  },
  {
    "name": "新白鹿餐厅",
    "area": "武林",
    "taste": "咸鲜",
    "mealType": "正餐",
    "avgPrice": 65,
    "isLocalFavorite": true,
    "isInfluencerHype": false,
    "reason": "性价比杭帮菜，蛋黄鸡翅人气高",
    "avoidTips": null,
    "bookingUrl": "https://m.dianping.com/shoplist/0/searchkeyword_%E6%96%B0%E7%99%BD%E9%B9%BF%E9%A4%90%E5%8E%85%20%E6%AD%A6%E6%9E%97",
    "address": "杭州市下城区武林广场",
    "latitude": 30.2641,
    "longitude": 120.1701,
    "platform": "大众点评"
  },
  {
    "name": "葱包桧",
    "area": "河坊街",
    "taste": "咸香",
    "mealType": "小吃",
    "avgPrice": 8,
    "isLocalFavorite": true,
    "isInfluencerHype": false,
    "reason": "河坊街传统小吃，现做现吃",
    "avoidTips": null,
    "bookingUrl": "https://m.dianping.com/shoplist/0/searchkeyword_%E8%91%B1%E5%8C%85%E6%A1%A7%20%E6%B2%B3%E5%9D%8A%E8%A1%97",
    "address": "杭州市上城区河坊街",
    "latitude": 30.2821,
    "longitude": 120.1751,
    "platform": "大众点评"
  },
  {
    "name": "龙井村农家菜",
    "area": "龙井",
    "taste": "清淡",
    "mealType": "正餐",
    "avgPrice": 85,
    "isLocalFavorite": true,
    "isInfluencerHype": false,
    "reason": "茶香入菜，环境清幽",
    "avoidTips": null,
    "bookingUrl": "https://m.dianping.com/shoplist/0/searchkeyword_%E9%BE%99%E4%BA%95%E6%9D%91%E5%86%9C%E5%AE%B6%E8%8F%9C%20%E9%BE%99%E4%BA%95",
    "address": "杭州市西湖区龙井村",
    "latitude": 30.2941,
    "longitude": 120.1401,
    "platform": "大众点评"
  }
]
